youtube_short_search/__init__.py
youtube_short_search/exceptions.py
youtube_short_search/searcher.py
youtube_short_search_package-0.1.0.dist-info/licenses/LICENSE
youtube_short_search_package-0.1.0.dist-info/METADATA
youtube_short_search_package-0.1.0.dist-info/WHEEL
youtube_short_search_package-0.1.0.dist-info/top_level.txt
youtube_short_search_package-0.1.0.dist-info/RECORD
